{
    "posts": [
        {
            "id": "4",
            "title": "Testing a 4th ",
            "date": "December 17,2024 9:53:30 PM",
            "body": "Some more testing words"
        },
        {
            "id": "5",
            "title": "hell",
            "date": "December 18,2024 11:51:38 PM",
            "body": "how are u"
        },
        {
            "id": "7",
            "title": "ra",
            "date": "December 21,2024 4:14:44 PM",
            "body": "rag"
        },
        {
            "id": "8",
            "title": "ranjith",
            "date": "December 21,2024 4:17:35 PM",
            "body": "thtryj"
        }
    ]
}